[{"codProducto":1,"nomProducto":"Termo Kovea Black Stone","precio":3059.0,"desc":"Termo de acero inoxidable con apertura por boton","color":"Negro","stockProducto":17,"categoria":"Termos","precioDosCinco":2967.23,"precioSeisDiez":2906.05,"precioDiezMas":2844.87,"estaOferta":true,"desOferta":"OFERTA DIA DE LA TRADICION 10% DESCUENTO","precioOferta":2753.10,"fechaInOferta":"2021-10-30T00:00:00","fechaFinOferta":"2021-12-20T00:00:00"},{"codProducto":2,"nomProducto":"Mate Original Stanley","precio":5900.0,"desc":"Mate termico de acero inoxidable","color":"Verde","stockProducto":50,"categoria":"Mates","precioDosCinco":5723.00,"precioSeisDiez":5605.00,"precioDiezMas":5487.00,"estaOferta":true,"desOferta":"OFERTA DIA DE LA TRADICION 10% DESCUENTO","precioOferta":5310.00,"fechaInOferta":"2021-10-30T00:00:00","fechaFinOferta":"2021-12-20T00:00:00"},{"codProducto":3,"nomProducto":"Termo original Stanley","precio":13900.0,"desc":"Termo de acero inoxidable con sistema antigoteo y con tapon cebador","color":"Verde","stockProducto":30,"categoria":"Termos","precioDosCinco":13483.00,"precioSeisDiez":13205.00,"precioDiezMas":12927.00,"estaOferta":true,"desOferta":"OFERTA DIA DEL PADRE 10% DESCUENTO","precioOferta":12510.00,"fechaInOferta":"2021-10-30T00:00:00","fechaFinOferta":"2021-12-20T00:00:00"},{"codProducto":4,"nomProducto":"Bombilla Pico De Loro","precio":690.0,"desc":"Bombilla Alpaca Brasilera con correcta disipacion de calor","color":"Plateado","stockProducto":50,"categoria":"Bombillas","precioDosCinco":669.30,"precioSeisDiez":655.50,"precioDiezMas":641.70,"estaOferta":true,"desOferta":"OFERTA DIA DE LA TRADICION 10% DESCUENTO","precioOferta":621.00,"fechaInOferta":"2021-10-30T00:00:00","fechaFinOferta":"2021-12-20T00:00:00"}]